criteria/__init__.py
criteria/criteria_performance.py
criteria_performance-1.3.5.dist-info/LICENSE
criteria_performance-1.3.5.dist-info/METADATA
criteria_performance-1.3.5.dist-info/WHEEL
criteria_performance-1.3.5.dist-info/top_level.txt
criteria_performance-1.3.5.dist-info/RECORD
