Metadata-Version: 2.1
Name: criteria_performance
Version: 1.3.5
Summary: A Python package for performance criteria visualization
Home-page: https://github.com/teach-genius/aryad.git
Author: Olanda-Eyiba Chantry
Author-email: chantryolanda85@gmail.com
License: MIT
Classifier: Programming Language :: Python :: 3
Classifier: License :: OSI Approved :: MIT License
Classifier: Operating System :: OS Independent
Requires-Python: >=3.6
License-File: LICENSE
Requires-Dist: numpy
Requires-Dist: pandas
Requires-Dist: matplotlib
Requires-Dist: mplcursors
